{
  "today": {
    "sunrise": "2024-08-18T06:14:22-06:00",
    "sunset": "2024-08-18T19:53:38-06:00",
    "solar_noon": "2024-08-18T13:04:00-06:00",
    "day_length": 49156,
    "civil_twilight_begin": "2024-08-18T05:47:10-06:00",
    "civil_twilight_end": "2024-08-18T20:20:51-06:00",
    "nautical_twilight_begin": "2024-08-18T05:12:35-06:00",
    "nautical_twilight_end": "2024-08-18T20:55:26-06:00",
    "astronomical_twilight_begin": "2024-08-18T04:35:49-06:00",
    "astronomical_twilight_end": "2024-08-18T21:32:11-06:00"
  },
  "tomorrow": {
    "sunrise": "2024-08-19T06:15:20-06:00",
    "sunset": "2024-08-19T19:52:13-06:00",
    "solar_noon": "2024-08-19T13:03:46-06:00",
    "day_length": 49013,
    "civil_twilight_begin": "2024-08-19T05:48:11-06:00",
    "civil_twilight_end": "2024-08-19T20:19:21-06:00",
    "nautical_twilight_begin": "2024-08-19T05:13:44-06:00",
    "nautical_twilight_end": "2024-08-19T20:53:48-06:00",
    "astronomical_twilight_begin": "2024-08-19T04:37:11-06:00",
    "astronomical_twilight_end": "2024-08-19T21:30:22-06:00"
  },
  "last_updated": 1724007900,
  "written_at": 1724007906
}